README
setup.py
routines/__init__.py
routines.egg-info/PKG-INFO
routines.egg-info/SOURCES.txt
routines.egg-info/dependency_links.txt
routines.egg-info/top_level.txt