Metadata-Version: 1.0
Name: routines
Version: 0.0.1
Summary: Routines is a simple package that provides a single decorator for you to mark functions as tasks (routines) that should be executed on a regular schedule.
Home-page: http://packages.python.org/routines
Author: Jonathan Enzinna
Author-email: jonnyfunfun@gmail.com
License: GPL
Keywords: recurrence reoccuring routines routine tasks
Platform: UNKNOWN
Classifier: Development Status :: 4 - Beta
Classifier: Topic :: Software Development :: Libraries :: Python Modules
Classifier: License :: OSI Approved :: GNU General Public License (GPL)
Classifier: Intended Audience :: Developers
Classifier: Operating System :: OS Independent
